{
  "generatedAt": "2026-07-15T17:20:43.773Z",
  "channels": [
    {
      "id": "agendafreetv",
      "name": "Agenda-Free TV",
      "channelId": "UCshCsg1YVKli8yBai-wa78w",
      "live": false
    },
    {
      "id": "forbesbreakingnews",
      "name": "Forbes Breaking News",
      "channelId": "UCg40OxZ1GYh3u3jBntB6DLg",
      "live": true,
      "videoId": "QFoDJovuCn0",
      "title": "LIVE: Trump Holds Public Event As US Renews Strikes On Iran, Todd Blanche Testifies Before Congress",
      "thumbnail": "https://i.ytimg.com/vi/QFoDJovuCn0/hqdefault.jpg"
    },
    {
      "id": "cspan",
      "name": "C-SPAN",
      "channelId": "UCb--64Gl51jIEVE-GLDAVTg",
      "live": true,
      "videoId": "hqId8YLImYc",
      "title": "Todd Blanche Senate Confirmation Hearing to be Attorney General",
      "thumbnail": "https://i.ytimg.com/vi/hqId8YLImYc/hqdefault.jpg"
    },
    {
      "id": "foxnews",
      "name": "Fox News",
      "channelId": "UCXIJgqnII2ZOINSWNOGFThA",
      "live": true,
      "videoId": "IDHN-O9Dlzw",
      "title": "WATCH LIVE: Trump AG nominee Todd Blanche testifies before Senate",
      "thumbnail": "https://i.ytimg.com/vi/IDHN-O9Dlzw/hqdefault.jpg"
    },
    {
      "id": "nypost",
      "name": "New York Post",
      "channelId": "UCrvhNP_lWuPIP6QZzJmM-bw",
      "live": true,
      "videoId": "d7TOKybPcfk",
      "title": "Watch Live: Todd Blanche Nominated to be Attorney General of the United States",
      "thumbnail": "https://i.ytimg.com/vi/d7TOKybPcfk/hqdefault.jpg"
    },
    {
      "id": "livenowfromfox",
      "name": "LiveNOW from FOX",
      "channelId": "UCyEUZXhmHr2rXGVHqX4gt7g",
      "live": false
    },
    {
      "id": "bbcnews",
      "name": "BBC News",
      "channelId": "UC16niRr50-MSBwiO3YDb3RA",
      "live": true,
      "videoId": "18BTC7RzEss",
      "title": "World Cup: Countdown to England v Argentina | BBC News",
      "thumbnail": "https://i.ytimg.com/vi/18BTC7RzEss/hqdefault.jpg"
    },
    {
      "id": "dailywire",
      "name": "The Daily Wire",
      "channelId": "UCaeO5vkdj5xOQHp4UmIN6dw",
      "live": false
    },
    {
      "id": "turningpointusa",
      "name": "Turning Point USA",
      "channelId": "UCVrK_pMRp_q8IelpfUCTGLQ",
      "live": false
    },
    {
      "id": "insideedition",
      "name": "Inside Edition",
      "channelId": "UC9k-yiEpRHMNVOnOi_aQK8w",
      "live": false
    },
    {
      "id": "frontline",
      "name": "FRONTLINE PBS",
      "channelId": "UC3ScyryU9Oy9Wse3a8OAmYQ",
      "live": false
    },
    {
      "id": "wsj",
      "name": "The Wall Street Journal",
      "channelId": "UCK7tptUDHh-RYDsdxO1-5QQ",
      "live": false
    },
    {
      "id": "nytimes",
      "name": "The New York Times",
      "channelId": "UCqnbDFdCpuN8CMEg0VuEBqA",
      "live": false
    },
    {
      "id": "associatedpress",
      "name": "Associated Press",
      "channelId": "UC52X5wxOL_s5yw0dQk7NtgA",
      "live": true,
      "videoId": "763ZT4sVSys",
      "title": "LIVE: Todd Blanche testifies at confirmation hearing to be attorney general",
      "thumbnail": "https://i.ytimg.com/vi/763ZT4sVSys/hqdefault.jpg"
    },
    {
      "id": "reuters",
      "name": "Reuters",
      "channelId": "UChqUTb7kYRX8-EiaN3XFrSQ",
      "live": true,
      "videoId": "Dtyj11KlZVo",
      "title": "LIVE: World Cup fans in Buenos Aires gather to watch Argentina-England semi-final",
      "thumbnail": "https://i.ytimg.com/vi/Dtyj11KlZVo/hqdefault.jpg"
    },
    {
      "id": "abcnews",
      "name": "ABC News",
      "channelId": "UCBi2mrWuNuyYy4gbM6fU18Q",
      "live": true,
      "videoId": "54f1LPXN8jk",
      "title": "Acting AG Todd Blanche testifies at his confirmation hearing",
      "thumbnail": "https://i.ytimg.com/vi/54f1LPXN8jk/hqdefault.jpg"
    },
    {
      "id": "nbcnews",
      "name": "NBC News",
      "channelId": "UCeY0bbntWzzVIaj2z3QigXg",
      "live": true,
      "videoId": "F_t7BjECg8M",
      "title": "LIVE: Todd Blanche confirmation hearing for attorney general",
      "thumbnail": "https://i.ytimg.com/vi/F_t7BjECg8M/hqdefault.jpg"
    },
    {
      "id": "cbsnews",
      "name": "CBS News",
      "channelId": "UC8p1vwvWtl6T73JiExfWs1g",
      "live": true,
      "videoId": "bUT5-q4LhDU",
      "title": "Watch Live: Todd Blanche faces questions at his Senate confirmation hearing for attorney general",
      "thumbnail": "https://i.ytimg.com/vi/bUT5-q4LhDU/hqdefault.jpg"
    },
    {
      "id": "cnn",
      "name": "CNN",
      "channelId": "UCupvZG-5ko_eiXAupbDfxWw",
      "live": true,
      "videoId": "UKSOQtqeHx4",
      "title": "Live: Todd Blanche AG confirmation hearing",
      "thumbnail": "https://i.ytimg.com/vi/UKSOQtqeHx4/hqdefault.jpg"
    },
    {
      "id": "msnow",
      "name": "MS NOW",
      "channelId": "UCaXkIU1QidjPwiAYu6GcHjg",
      "live": true,
      "videoId": "31OoMFrYSBw",
      "title": "LIVE: Trump’s controversial AG pick Todd Blanche testifies at confirmation hearing",
      "thumbnail": "https://i.ytimg.com/vi/31OoMFrYSBw/hqdefault.jpg"
    },
    {
      "id": "skynews",
      "name": "Sky News",
      "channelId": "UCoMdktPbSTixAyNGwb-UYkQ",
      "live": true,
      "videoId": "JI1dWDbUXzc",
      "title": "Fans arrive for England vs Argentina World Cup semi-final",
      "thumbnail": "https://i.ytimg.com/vi/JI1dWDbUXzc/hqdefault.jpg"
    },
    {
      "id": "aljazeeraenglish",
      "name": "Al Jazeera English",
      "channelId": "UCNye-wNBqNL5ZzHSJj3l8Bg",
      "live": true,
      "videoId": "gCNeDWCI0vo",
      "title": "🔴 Al Jazeera English | Live",
      "thumbnail": "https://i.ytimg.com/vi/gCNeDWCI0vo/hqdefault.jpg"
    },
    {
      "id": "dwnews",
      "name": "DW News",
      "channelId": "UCknLrEdhRCp1aegoMqRaCZg",
      "live": true,
      "videoId": "LuKwFajn37U",
      "title": "DW News livestream | Headline news from around the world",
      "thumbnail": "https://i.ytimg.com/vi/LuKwFajn37U/hqdefault.jpg"
    },
    {
      "id": "france24-en",
      "name": "FRANCE 24 English",
      "channelId": "UCQfwfsi5VrQ8yKZ-UWmAEFg",
      "live": true,
      "videoId": "HvZt-nh9sGg",
      "title": "FRANCE 24 English – LIVE – International Breaking News & Top stories - 24/7 stream",
      "thumbnail": "https://i.ytimg.com/vi/HvZt-nh9sGg/hqdefault.jpg"
    },
    {
      "id": "bloomberg-tv",
      "name": "Bloomberg Television",
      "channelId": "UCIALMKvObZNtJ6AmdCLP7Lg",
      "live": true,
      "videoId": "QB5BNdBFujE",
      "title": "Bloomberg Business News Live",
      "thumbnail": "https://i.ytimg.com/vi/QB5BNdBFujE/hqdefault.jpg"
    },
    {
      "id": "cnbc",
      "name": "CNBC",
      "channelId": "UCvJJ_dzjViJCoLf5uKUTwoA",
      "live": true,
      "videoId": "9NyxcX3rhQs",
      "title": "LIVE: CNBC Marathon - Documentaries and deep dives 24/7",
      "thumbnail": "https://i.ytimg.com/vi/9NyxcX3rhQs/hqdefault.jpg"
    },
    {
      "id": "pbsnewshour",
      "name": "PBS NewsHour",
      "channelId": "UC6ZFN9Tx6xh-skXCuRHCDpQ",
      "live": true,
      "videoId": "rgogiEsHvmM",
      "title": "WATCH LIVE: Todd Blanche testifies in confirmation hearing for attorney general",
      "thumbnail": "https://i.ytimg.com/vi/rgogiEsHvmM/hqdefault.jpg"
    },
    {
      "id": "newsnation",
      "name": "NewsNation",
      "channelId": "UCCjG8NtOig0USdrT5D1FpxQ",
      "live": true,
      "videoId": "403cLrPPYcY",
      "title": "Can the Dems outrun the DSA? Debate with Mally Smith | Prove it! with Batya",
      "thumbnail": "https://i.ytimg.com/vi/403cLrPPYcY/hqdefault.jpg"
    },
    {
      "id": "scrippsnews",
      "name": "Scripps News",
      "channelId": "UCTln5ss6h6L_xNfMeujfPbg",
      "live": true,
      "videoId": "2NMizlhDZDY",
      "title": "LIVE: Top Headlines You Need to Know Today",
      "thumbnail": "https://i.ytimg.com/vi/2NMizlhDZDY/hqdefault.jpg"
    },
    {
      "id": "guardiannews",
      "name": "Guardian News",
      "channelId": "UCIRYBXDze5krPDzAEOxFGVA",
      "live": true,
      "videoId": "U_aPkayoMLA",
      "title": "Blanche testifies in two-day Senate confirmation hearing - watch live",
      "thumbnail": "https://i.ytimg.com/vi/U_aPkayoMLA/hqdefault.jpg"
    },
    {
      "id": "channel4news",
      "name": "Channel 4 News",
      "channelId": "UCTrQ7HXWRRxr7OsOtodr2_w",
      "live": false
    },
    {
      "id": "globalnews",
      "name": "Global News",
      "channelId": "UChLtXXpo4Ge1ReTEboVvTDg",
      "live": true,
      "videoId": "YQ8e7C4eH1A",
      "title": "Champagne speaks to media as provincial, territorial finance ministers meet in PEI | LIVE",
      "thumbnail": "https://i.ytimg.com/vi/YQ8e7C4eH1A/hqdefault.jpg"
    },
    {
      "id": "cna",
      "name": "CNA",
      "channelId": "UC83jt4dlz1Gjl58fzQrrKZg",
      "live": true,
      "videoId": "XWq5kBlakcQ",
      "title": "[CNA 24/7 LIVE] Breaking news on Asia and award-winning documentaries and shows",
      "thumbnail": "https://i.ytimg.com/vi/XWq5kBlakcQ/hqdefault.jpg"
    }
  ],
  "health": {
    "last24h": {
      "runs": 22,
      "channelChecks": 414,
      "errors": 30
    },
    "lastRun": {
      "at": "2026-07-15T17:20:43.773Z",
      "checked": 33,
      "errors": 0
    }
  }
}
